ai_models/__init__.py
ai_models/ai_models.py
ai_pipelines/__init__.py
ai_pipelines/ai_pipelines.py
ai_transformers/__init__.py
ai_transformers/ai_transformers.py
datapoints/__init__.py
datapoints/datapoints.py
datasets/__init__.py
datasets/datasets.py
entities/__init__.py
entities/entities.py
rules/__init__.py
rules/rules.py
test/__init__.py
test/ownworld.py
test/test_steps_cucumber.py
timeseries/__init__.py
timeseries/timeseries.py
ogapi_py-0.0.1.dist-info/METADATA
ogapi_py-0.0.1.dist-info/WHEEL
ogapi_py-0.0.1.dist-info/top_level.txt
ogapi_py-0.0.1.dist-info/RECORD
